{
  "version": 1,
  "license": "CC-BY-SA-3.0",
  "copyright": "Taken from /tg/station",
  "size": {
    "x": 32,
    "y": 32
  },
  "states": [
    {
      "name": "hierophant_blast-begin",
      "directions": 4,
      "delays": [
        [ 0.1, 0.08, 0.06, 0.04, 0.02, 0.125, 0.175 ],
        [ 0.1, 0.08, 0.06, 0.04, 0.02, 0.125, 0.175 ],
        [ 0.1, 0.08, 0.06, 0.04, 0.02, 0.125, 0.175 ],
        [ 0.1, 0.08, 0.06, 0.04, 0.02, 0.125, 0.175 ]
      ]
    },
    {
      "name": "hierophant_blast-end",
      "directions": 4,
      "delays": [
        [ 0.15, 0.1, 0.025, 0.05 ],
        [ 0.15, 0.1, 0.025, 0.05 ],
        [ 0.15, 0.1, 0.025, 0.05 ],
        [ 0.15, 0.1, 0.025, 0.05 ]
      ]
    }
  ]
}
