{
    "version": 1,
    "license": "CC-BY-SA-3.0",
    "copyright": "https://github.com/tgstation/tgstation/pull/84126/commits/979251010a6f2ebbbece5f94149a071aadcc4e0a.",
    "size": {
        "x": 32,
        "y": 32
    },
    "states": [
        {
            "name": "icon",
            "directions": 1
        },
        {
            "name": "icon-on",
            "directions": 1,
            "delays": [
                [
                    0.2,
                    0.2
                ]
            ]
        },
        {
            "name": "inhand-left",
            "directions": 4
        },
        {
            "name": "inhand-right",
            "directions": 4
        },
        {
            "name": "equipped-BACKPACK",
            "directions": 4
        },
        {
            "name": "on-equipped-BACKPACK",
            "directions": 4,
            "delays": [
                [
                    0.2,
                    0.2
                ],
                [
                    0.2,
                    0.2
                ],
                [
                    0.2,
                    0.2
                ],
                [
                    0.2,
                    0.2
                ]
            ]
        }
    ]
}
